setup.cfg
setup.py
noise_generator/__init__.py
noise_generator/matrix_generator.py
noise_generator.egg-info/PKG-INFO
noise_generator.egg-info/SOURCES.txt
noise_generator.egg-info/dependency_links.txt
noise_generator.egg-info/not-zip-safe
noise_generator.egg-info/top_level.txt