Metadata-Version: 1.0
Name: noise-generator
Version: 0.0
Summary: Diiferent audio and matrix generator
Home-page: UNKNOWN
Author: UNKNOWN
Author-email: work.demen1205@gmail.com
License: UNKNOWN
Platform: UNKNOWN
